tornado_fluent.py
tornado_fluent-0.1.2.dist-info/LICENSE
tornado_fluent-0.1.2.dist-info/METADATA
tornado_fluent-0.1.2.dist-info/WHEEL
tornado_fluent-0.1.2.dist-info/top_level.txt
tornado_fluent-0.1.2.dist-info/RECORD
