Metadata-Version: 2.1
Name: tornado-fluent
Version: 0.1.2
Summary: Async Fluentd client for Tornado 4-5
Home-page: http://github.com/sockeye44/tornado_fluent
Author: Alexander Zelenin
Author-email: az@inten.to
License: bsd
Platform: UNKNOWN
Requires-Python: >=3.3
Requires-Dist: msgpack-python (>=0.4.8)
Requires-Dist: tornado (>=4)
